design.sv
module async_fifo #(
    parameter DATA_WIDTH = 8,
    parameter ADDR_WIDTH = 4
)(
    input                   wr_clk,
    input                   rd_clk,
    input                   rst,

    input                   wr_en,
    input                   rd_en,

    input  [DATA_WIDTH-1:0] din,
    output reg [DATA_WIDTH-1:0] dout,

    output full,
    output empty
);

localparam DEPTH = 1 << ADDR_WIDTH;

// Memory
reg [DATA_WIDTH-1:0] mem [0:DEPTH-1];

// Binary pointers
reg [ADDR_WIDTH:0] wr_ptr_bin, rd_ptr_bin;

// Gray pointers
reg [ADDR_WIDTH:0] wr_ptr_gray, rd_ptr_gray;

// Synchronized pointers
reg [ADDR_WIDTH:0] wr_gray_sync1, wr_gray_sync2;
reg [ADDR_WIDTH:0] rd_gray_sync1, rd_gray_sync2;

// Binary → Gray
function [ADDR_WIDTH:0] bin2gray;
    input [ADDR_WIDTH:0] bin;
begin
    bin2gray = (bin >> 1) ^ bin;
end
endfunction


// Write Logic

always @(posedge wr_clk or posedge rst)
begin
    if(rst) begin
        wr_ptr_bin  <= 0;
        wr_ptr_gray <= 0;
    end
    else if(wr_en && !full) begin
        mem[wr_ptr_bin[ADDR_WIDTH-1:0]] <= din;
        wr_ptr_bin  <= wr_ptr_bin + 1;
        wr_ptr_gray <= bin2gray(wr_ptr_bin + 1);
    end
end


// Read Logic

always @(posedge rd_clk or posedge rst)
begin
    if(rst) begin
        rd_ptr_bin  <= 0;
        rd_ptr_gray <= 0;
        dout <= 0;
    end
    else if(rd_en && !empty) begin
        dout <= mem[rd_ptr_bin[ADDR_WIDTH-1:0]];
        rd_ptr_bin  <= rd_ptr_bin + 1;
        rd_ptr_gray <= bin2gray(rd_ptr_bin + 1);
    end
end


// Synchronize Read Pointer into Write Clock Domain

always @(posedge wr_clk or posedge rst)
begin
    if(rst) begin
        rd_gray_sync1 <= 0;
        rd_gray_sync2 <= 0;
    end
    else begin
        rd_gray_sync1 <= rd_ptr_gray;
        rd_gray_sync2 <= rd_gray_sync1;
    end
end


// Synchronize Write Pointer into Read Clock Domain

always @(posedge rd_clk or posedge rst)
begin
    if(rst) begin
        wr_gray_sync1 <= 0;
        wr_gray_sync2 <= 0;
    end
    else begin
        wr_gray_sync1 <= wr_ptr_gray;
        wr_gray_sync2 <= wr_gray_sync1;
    end
end


// Empty Detection

assign empty = (rd_ptr_gray == wr_gray_sync2);


// Full Detection

wire [ADDR_WIDTH:0] wr_gray_next;

assign wr_gray_next = bin2gray(wr_ptr_bin + 1);

assign full =
    (wr_gray_next ==
    {~rd_gray_sync2[ADDR_WIDTH:ADDR_WIDTH-1],
      rd_gray_sync2[ADDR_WIDTH-2:0]});

endmodule

testbench.sv
`timescale 1ns/1ps

module tb_async_fifo;

parameter DATA_WIDTH = 8;
parameter ADDR_WIDTH = 4;

reg wr_clk;
reg rd_clk;
reg rst;
reg wr_en;
reg rd_en;
reg [DATA_WIDTH-1:0] din;

wire [DATA_WIDTH-1:0] dout;
wire full;
wire empty;

async_fifo #(
.DATA_WIDTH(DATA_WIDTH),
.ADDR_WIDTH(ADDR_WIDTH)
)dut(
.wr_clk(wr_clk),
.rd_clk(rd_clk),
.rst(rst),
.wr_en(wr_en),
.rd_en(rd_en),
.din(din),
.dout(dout),
.full(full),
.empty(empty)
);

// Write clock =100MHz
always #5 wr_clk = ~wr_clk;

// Read clock =71MHz
always #7 rd_clk = ~rd_clk;

initial begin
    $dumpfile("dump.vcd");
    $dumpvars(0,tb_async_fifo);

    wr_clk=0;
    rd_clk=0;
    rst=1;
    wr_en=0;
    rd_en=0;
    din=0;

    #20;
    rst=0;

    
    // Write 10 values
    
    repeat(10)
    begin
        @(posedge wr_clk);
        wr_en=1;
        din=din+1;
    end

    @(posedge wr_clk);
    wr_en=0;

    #30;

  
    // Read 10 values
   
    repeat(10)
    begin
        @(posedge rd_clk);
        rd_en=1;
    end

    @(posedge rd_clk);
    rd_en=0;

    #100;

    $finish;
end

initial begin
    $monitor("T=%0t WR=%b RD=%b DIN=%h DOUT=%h FULL=%b EMPTY=%b",
    $time,wr_en,rd_en,din,dout,full,empty);
end

endmodule

simulation/dump.vcd
$date
	Wed Jul 15 23:52:14 2026
$end
$version
	Icarus Verilog
$end
$timescale
	1ps
$end
$scope module tb_async_fifo $end
$var wire 1 ! full $end
$var wire 1 " empty $end
$var wire 8 # dout [7:0] $end
$var parameter 32 $ ADDR_WIDTH $end
$var parameter 32 % DATA_WIDTH $end
$var reg 8 & din [7:0] $end
$var reg 1 ' rd_clk $end
$var reg 1 ( rd_en $end
$var reg 1 ) rst $end
$var reg 1 * wr_clk $end
$var reg 1 + wr_en $end
$scope module dut $end
$var wire 8 , din [7:0] $end
$var wire 1 ' rd_clk $end
$var wire 1 ( rd_en $end
$var wire 1 ) rst $end
$var wire 1 * wr_clk $end
$var wire 1 + wr_en $end
$var wire 5 - wr_gray_next [4:0] $end
$var wire 1 ! full $end
$var wire 1 " empty $end
$var parameter 32 . ADDR_WIDTH $end
$var parameter 32 / DATA_WIDTH $end
$var parameter 36 0 DEPTH $end
$var reg 8 1 dout [7:0] $end
$var reg 5 2 rd_gray_sync1 [4:0] $end
$var reg 5 3 rd_gray_sync2 [4:0] $end
$var reg 5 4 rd_ptr_bin [4:0] $end
$var reg 5 5 rd_ptr_gray [4:0] $end
$var reg 5 6 wr_gray_sync1 [4:0] $end
$var reg 5 7 wr_gray_sync2 [4:0] $end
$var reg 5 8 wr_ptr_bin [4:0] $end
$var reg 5 9 wr_ptr_gray [4:0] $end
$scope function bin2gray $end
$var reg 5 : bin [4:0] $end
$upscope $end
$upscope $end
$upscope $end
$enddefinitions $end
$comment Show the parameter values. $end
$dumpall
b10000 0
b1000 /
b100 .
b1000 %
b100 $
$end
#0
$dumpvars
b1 :
b0 9
b0 8
b0 7
b0 6
b0 5
b0 4
b0 3
b0 2
b0 1
b1 -
b0 ,
0+
0*
1)
0(
0'
b0 &
b0 #
1"
0!
$end
#5000
1*
#7000
1'
#10000
0*
#14000
0'
#15000
1*
#20000
0*
0)
#21000
1'
#25000
b11 -
b10 :
b1 9
b1 8
b1 &
b1 ,
1+
1*
#28000
0'
#30000
0*
#35000
b10 -
b11 :
b11 9
b10 8
b1 6
b10 &
b10 ,
1*
1'
#40000
0*
#42000
0'
#45000
b110 -
b100 :
b10 9
b11 8
b11 &
b11 ,
1*
#49000
0"
b1 7
b10 6
1'
#50000
0*
#55000
b111 -
b101 :
b110 9
b100 8
b100 &
b100 ,
1*
#56000
0'
#60000
0*
#63000
b10 7
b110 6
1'
#65000
b101 -
b110 :
b111 9
b101 8
b101 &
b101 ,
1*
#70000
0*
0'
#75000
b100 -
b111 :
b101 9
b110 8
b110 &
b110 ,
1*
#77000
b110 7
b101 6
1'
#80000
0*
#84000
0'
#85000
b1100 -
b1000 :
b100 9
b111 8
b111 &
b111 ,
1*
#90000
0*
#91000
b101 7
b100 6
1'
#95000
b1101 -
b1001 :
b1100 9
b1000 8
b1000 &
b1000 ,
1*
#98000
0'
#100000
0*
#105000
b1111 -
b1010 :
b1101 9
b1001 8
b100 7
b1100 6
b1001 &
b1001 ,
1*
1'
#110000
0*
#112000
0'
#115000
b1110 -
b1011 :
b1111 9
b1010 8
b1010 &
b1010 ,
1*
#119000
b1100 7
b1111 6
1'
#120000
0*
#125000
0+
1*
#126000
0'
#130000
0*
#133000
b1111 7
1'
#135000
1*
#140000
0*
0'
#145000
1*
#147000
1'
#150000
0*
#154000
0'
#155000
1*
#160000
0*
#161000
b1 5
b1 4
b1 #
b1 1
b1 :
1(
1'
#165000
b1 2
1*
#168000
0'
#170000
0*
#175000
b1 3
b11 5
b10 4
b10 #
b10 1
b10 :
1*
1'
#180000
0*
#182000
0'
#185000
b11 2
1*
#189000
b10 5
b11 4
b11 #
b11 1
b11 :
1'
#190000
0*
#195000
b11 3
b10 2
1*
#196000
0'
#200000
0*
#203000
b110 5
b100 4
b100 #
b100 1
b100 :
1'
#205000
b10 3
b110 2
1*
#210000
0*
0'
#215000
b110 3
1*
#217000
b111 5
b101 4
b101 #
b101 1
b101 :
1'
#220000
0*
#224000
0'
#225000
b111 2
1*
#230000
0*
#231000
b101 5
b110 4
b110 #
b110 1
b110 :
1'
#235000
b111 3
b101 2
1*
#238000
0'
#240000
0*
#245000
b101 3
b100 5
b111 4
b111 #
b111 1
b111 :
1*
1'
#250000
0*
#252000
0'
#255000
b100 2
1*
#259000
b1100 5
b1000 4
b1000 #
b1000 1
b1000 :
1'
#260000
0*
#265000
b100 3
b1100 2
1*
#266000
0'
#270000
0*
#273000
b1101 5
b1001 4
b1001 #
b1001 1
b1001 :
1'
#275000
b1100 3
b1101 2
1*
#280000
0*
0'
#285000
b1101 3
1*
#287000
1"
b1111 5
b1010 4
b1010 #
b1010 1
b1010 :
1'
#290000
0*
#294000
0'
#295000
b1111 2
1*
#300000
0*
#301000
0(
1'
#305000
b1111 3
1*
